IBBCoreLogger/IBBCoreLogger.py
IBBCoreLogger/__init__.py
CoreLogger-1.0.10.dist-info/METADATA
CoreLogger-1.0.10.dist-info/WHEEL
CoreLogger-1.0.10.dist-info/top_level.txt
CoreLogger-1.0.10.dist-info/RECORD
