Metadata-Version: 2.1
Name: CoreLogger
Version: 1.0.10
Summary: A simple logger for sending logs to a Loki server for Internal use at IZBB.
Home-page: https://pypi.org/project/CoreLogger
Author: Ahmet Kıpkıp
Author-email: ahmtkipkip@gmail.com
Classifier: Programming Language :: Python :: 3.8
Classifier: Operating System :: OS Independent
Requires-Python: >=3.8
Requires-Dist: python-logging-loki
